ipychess/__init__.py
ipychess/board.py
ipychess/nav.py
ipychess/observable.py
ipychess-0.1.0.dist-info/METADATA
ipychess-0.1.0.dist-info/WHEEL
ipychess-0.1.0.dist-info/top_level.txt
ipychess-0.1.0.dist-info/RECORD
