Metadata-Version: 2.1
Name: ipychess
Version: 0.1.0
Summary: IPython chess displays
Author-email: Marcel Claramunt <marcel@moveread.com>
Project-URL: repo, https://github.com/moveread/REPO.git
Requires-Python: >=3.10
Requires-Dist: chess
Requires-Dist: ipywidgets
